lakers_python-0.5.0.dist-info/METADATA
lakers_python-0.5.0.dist-info/WHEEL
lakers/__init__.py
lakers/lakers.cpython-310-x86_64-linux-gnu.so
lakers_python-0.5.0.dist-info/RECORD
