Metadata-Version: 2.4
Name: lakers-python
Version: 0.5.0
License: BSD-3-Clause
Project-URL: Source Code, https://github.com/openwsn-berkeley/lakers/
